{
  "version": "7",
  "dialect": "sqlite",
  "entries": [
    {
      "idx": 0,
      "version": "6",
      "when": 1776180438577,
      "tag": "0000_nice_supreme_intelligence",
      "breakpoints": true
    },
    {
      "idx": 1,
      "version": "6",
      "when": 1776395032677,
      "tag": "0001_sour_sunset_bain",
      "breakpoints": true
    },
    {
      "idx": 2,
      "version": "6",
      "when": 1776416150620,
      "tag": "0002_regular_wallow",
      "breakpoints": true
    },
    {
      "idx": 3,
      "version": "6",
      "when": 1776417642309,
      "tag": "0003_acoustic_loners",
      "breakpoints": true
    },
    {
      "idx": 4,
      "version": "6",
      "when": 1776420312544,
      "tag": "0004_lucky_red_wolf",
      "breakpoints": true
    },
    {
      "idx": 5,
      "version": "6",
      "when": 1777100000000,
      "tag": "0005_typed_edges",
      "breakpoints": true
    },
    {
      "idx": 6,
      "version": "6",
      "when": 1777200000000,
      "tag": "0006_access_telemetry",
      "breakpoints": true
    },
    {
      "idx": 7,
      "version": "6",
      "when": 1777300000000,
      "tag": "0007_work_layer",
      "breakpoints": true
    },
    {
      "idx": 8,
      "version": "6",
      "when": 1777400000000,
      "tag": "0008_seq_id",
      "breakpoints": true
    },
    {
      "idx": 9,
      "version": "6",
      "when": 1777500000000,
      "tag": "0009_ingest_jobs",
      "breakpoints": true
    },
    {
      "idx": 10,
      "version": "6",
      "when": 1777600000000,
      "tag": "0010_chat_history",
      "breakpoints": true
    },
    {
      "idx": 11,
      "version": "6",
      "when": 1777700000000,
      "tag": "0011_api_keys",
      "breakpoints": true
    },
    {
      "idx": 12,
      "version": "6",
      "when": 1777800000000,
      "tag": "0012_ingest_job_id",
      "breakpoints": true
    },
    {
      "idx": 13,
      "version": "6",
      "when": 1777900000000,
      "tag": "0013_broken_links",
      "breakpoints": true
    },
    {
      "idx": 14,
      "version": "6",
      "when": 1778000000000,
      "tag": "0014_ingest_backend_columns",
      "breakpoints": true
    },
    {
      "idx": 15,
      "version": "6",
      "when": 1778100000000,
      "tag": "0015_tenant_secrets",
      "breakpoints": true
    },
    {
      "idx": 16,
      "version": "6",
      "when": 1778200000000,
      "tag": "0016_ingest_jobs_date_index",
      "breakpoints": true
    },
    {
      "idx": 17,
      "version": "6",
      "when": 1778300000000,
      "tag": "0017_ingest_jobs_cost_estimated",
      "breakpoints": true
    },
    {
      "idx": 18,
      "version": "6",
      "when": 1778400000000,
      "tag": "0018_documents_extract_cost",
      "breakpoints": true
    },
    {
      "idx": 19,
      "version": "6",
      "when": 1778500000000,
      "tag": "0019_documents_last_contradiction_scan",
      "breakpoints": true
    },
    {
      "idx": 20,
      "version": "6",
      "when": 1778600000000,
      "tag": "0020_documents_lint_signature",
      "breakpoints": true
    },
    {
      "idx": 21,
      "version": "6",
      "when": 1777127867344,
      "tag": "0021_chat_backend_columns",
      "breakpoints": true
    },
    {
      "idx": 22,
      "version": "6",
      "when": 1778800000000,
      "tag": "0022_tenant_credits",
      "breakpoints": true
    },
    {
      "idx": 23,
      "version": "6",
      "when": 1778900000000,
      "tag": "0023_chat_persona_overrides",
      "breakpoints": true
    },
    {
      "idx": 24,
      "version": "6",
      "when": 1779000000000,
      "tag": "0024_documents_content_hash",
      "breakpoints": true
    },
    {
      "idx": 25,
      "version": "6",
      "when": 1779100000000,
      "tag": "0025_document_images",
      "breakpoints": true
    },
    {
      "idx": 26,
      "version": "6",
      "when": 1779200000000,
      "tag": "0026_jobs_table",
      "breakpoints": true
    },
    {
      "idx": 27,
      "version": "6",
      "when": 1779300000000,
      "tag": "0027_vision_quality_ratings",
      "breakpoints": true
    }
  ]
}
